{"version": 0.6, "generator": "Overpass API 0.7.62.1 084b4234", "osm3s": {"timestamp_osm_base": "2024-04-07T13:01:45Z", "copyright": "The data included in this document is from www.openstreetmap.org. The data is made available under ODbL."}, "elements": [{"type": "node", "id": 1867990869, "lat": 55.8837695, "lon": 12.0006701}, {"type": "node", "id": 2382637589, "lat": 55.8839505, "lon": 12.0005176}, {"type": "way", "id": 229702936, "nodes": [2382637589, 1867990869], "tags": {"tunnel": "culvert", "waterway": "river"}}]}